erlang_changes/__init__.py
erlang_changes/changes.py
erlang_changes/cli.py
erlang_changes/github.py
erlang_changes/notes.py
erlang_changes/otp_src.py
erlang_changes/otp_versions_table.py
erlang_changes/spec.py
obs_service_erlang_changes-0.3.2.dist-info/licenses/LICENSE
usr/lib/obs/service/erlang_changes.service
obs_service_erlang_changes-0.3.2.dist-info/METADATA
obs_service_erlang_changes-0.3.2.dist-info/WHEEL
obs_service_erlang_changes-0.3.2.dist-info/entry_points.txt
obs_service_erlang_changes-0.3.2.dist-info/top_level.txt
obs_service_erlang_changes-0.3.2.dist-info/RECORD
