Metadata-Version: 2.4
Name: obs-service-erlang_changes
Version: 0.3.2
Summary: Erlang changelog formatting OBS service
Author-email: "Matwey V. Kornilov" <matwey.kornilov@gmail.com>
License: GPL-2.0
Project-URL: Repository, https://github.com/openSUSE/obs-service-erlang_changes.git
Project-URL: Issues, https://github.com/openSUSE/obs-service-erlang_changes/issues
Requires-Python: >=3.8
License-File: LICENSE
Requires-Dist: lxml
Requires-Dist: mistune>=3
Requires-Dist: requests
Requires-Dist: rpm
Provides-Extra: dev
Requires-Dist: freezegun; extra == "dev"
Requires-Dist: pytest; extra == "dev"
Dynamic: license-file
